Metadata-Version: 1.1
Name: ldicttools
Version: 0.1.0
Summary: Tools for searching/indexing dictionaries
Home-page: https://github.com/MineRobber9000/ldicttools
Author: Robert Miles
Author-email: milesrobert374@gmail.com
License: MIT
Keywords: index search words
Platform: UNKNOWN
Classifier: Development Status :: 4 - Beta
Classifier: License :: OSI Approved :: MIT License
Classifier: Programming Language :: Python :: 2
Classifier: Programming Language :: Python :: 2.7
